pypiactl/__init__.py
pypiactl/_background.py
pypiactl/_config.py
pypiactl/_constants.py
pypiactl/_dedicated_ip.py
pypiactl/_monitors.py
pypiactl/_types.py
pypiactl/_utils.py
pypiactl/pypiactl.py
pypiactl-3.6.1.1.dist-info/METADATA
pypiactl-3.6.1.1.dist-info/WHEEL
pypiactl-3.6.1.1.dist-info/licenses/LICENSE
pypiactl-3.6.1.1.dist-info/RECORD
