Metadata-Version: 2.4
Name: pypiactl
Version: 3.6.1.1
Summary: A wrapper for the command-line interface to the Private Internet Access (PIA) client.
Project-URL: Homepage, https://github.com/LumaDevelopment/pypiactl
Project-URL: Repository, https://github.com/LumaDevelopment/pypiactl
Author-email: Joshua Sheldon <12071794+LumaDevelopment@users.noreply.github.com>
License:                     GNU GENERAL PUBLIC LICENSE
License-File: LICENSE
Classifier: Development Status :: 3 - Alpha
Classifier: Intended Audience :: Developers
Classifier: License :: OSI Approved :: GNU General Public License v2 (GPLv2)
Classifier: Natural Language :: English
Classifier: Programming Language :: Python :: 3
Classifier: Programming Language :: Python :: 3.7
Classifier: Topic :: Internet
Classifier: Topic :: System :: Networking
Classifier: Topic :: System :: Shells
Classifier: Typing :: Typed
Requires-Python: >=3.7
Provides-Extra: dev
Requires-Dist: black; extra == 'dev'
Requires-Dist: isort; extra == 'dev'
Requires-Dist: mypy; extra == 'dev'
Provides-Extra: test
Requires-Dist: pytest-cov; extra == 'test'
Requires-Dist: pytest-mock; extra == 'test'
Requires-Dist: pytest>=7.0; extra == 'test'
